{
  "id": "checkbox-ASDFGHJKKL",
  "class": "checkbox-ASDFGHJKKL",
  "name": "",
  "discription": "",
  "component": "fb-widget-checkbox",
  "parent": "",
  "type": "form",
  "inputType": "text",
  "bindProperty": "",
  "show": "",
  "style": {
    "margin": "0px",
    "borderWidth": "1px 1px 1px 1px",
    "borderStyle": "solid",
    "borderColor": "#9a9393",
    "boxShadow": "0px 0px 0px 0px #000000"
  },
  "events": {},
  "sudoStyle": {
    "focus": {
      "borderColor": "blue"
    }
  },
  "addOnStyle": {},
  "staticStyle": ""
}